realcwpmat/__init__.py
realcwpmat/app.py
realcwpmat-1.0.4.dist-info/METADATA
realcwpmat-1.0.4.dist-info/WHEEL
realcwpmat-1.0.4.dist-info/top_level.txt
realcwpmat-1.0.4.dist-info/RECORD
