Metadata-Version: 2.1
Name: realcwpmat
Version: 1.0.4
Summary: 一个数学计算包
Home-page: https://github.com/pypa/sampleproject
Author: auth_cwpccna
Author-email: 623365663@qq.com
License: UNKNOWN
Platform: UNKNOWN
Classifier: Programming Language :: Python :: 3
Classifier: License :: OSI Approved :: MIT License
Classifier: Operating System :: OS Independent
